gedi_tools/__init__.py
gedi_tools/classes/__init__.py
gedi_tools/classes/l2b.py
gedi_tools/handlers/__init__.py
gedi_tools/handlers/cmr.py
gedi_tools/handlers/db.py
gedi_tools/handlers/hd5.py
gedi_tools-0.0.3.dist-info/LICENSE.md
gedi_tools-0.0.3.dist-info/METADATA
gedi_tools-0.0.3.dist-info/WHEEL
gedi_tools-0.0.3.dist-info/top_level.txt
gedi_tools-0.0.3.dist-info/RECORD
