Metadata-Version: 2.1
Name: gedi-tools
Version: 0.0.3
Summary: A python package to assist working with GEDI data.
Home-page: https://github.com/iosefa/gediTools
Author: Joseph Emile Honour Percival
Author-email: ipercival@gmail.com
Project-URL: Documentation, https://geditools.readthedocs.io/en/latest/
Project-URL: Source, https://github.com/iosefa/gediTools/
Project-URL: Bug Tracker, https://github.com/iosefa/gediTools/issues
Classifier: Programming Language :: Python :: 3
Classifier: License :: OSI Approved :: MIT License
Classifier: Operating System :: OS Independent
Requires-Python: >=3.10
License-File: LICENSE.md
Requires-Dist: pandas (~=1.5.3)
Requires-Dist: geopandas (~=0.12.2)
Requires-Dist: requests (~=2.28.2)
Requires-Dist: tqdm (~=4.64.1)
Requires-Dist: h5py (~=3.8.0)
Requires-Dist: numpy (~=1.24.2)
